plm_utils-0.1.4.dist-info/METADATA
plm_utils-0.1.4.dist-info/WHEEL
plm_utils-0.1.4.dist-info/entry_points.txt
plm_utils-0.1.4.dist-info/licenses/LICENSE
pu_utils/__init__.py
pu_utils/aws/__init__.py
pu_utils/aws/api/__init__.py
pu_utils/aws/api/_gateway.py
pu_utils/aws/api/_resource.py
pu_utils/aws/iam.py
pu_utils/aws/iam_test.py
pu_utils/aws/lambda_.py
pu_utils/namer.py
pu_utils/namer_test.py
pu_utils/python_zip.py
pu_utils/python_zip_test.py
plm_utils-0.1.4.dist-info/RECORD
