Metadata-Version: 2.1
Name: plm-utils
Version: 0.1.4
Summary: Random stuff to help writing Pulumi scripts easier
Author-Email: PTNGlobal <support@ptnglobalcorp.com>
License:                                  Apache License
Project-URL: Source, https://github.com/ptnglobalcorp/pulumi-utils
Requires-Python: >=3.12.0
Requires-Dist: pulumi
Requires-Dist: uv
Provides-Extra: dev
Requires-Dist: pyright; extra == "dev"
Requires-Dist: ruff; extra == "dev"
Requires-Dist: ward; extra == "dev"
Requires-Dist: twine; extra == "dev"
Requires-Dist: build; extra == "dev"
Provides-Extra: aws
Requires-Dist: pulumi-aws; extra == "aws"
